mengzi_zs/__init__.py
mengzi_zs/inference.py
mengzi_zs/prompts.py
mengzi_zero_shot-0.2.1.dist-info/LICENSE
mengzi_zero_shot-0.2.1.dist-info/METADATA
mengzi_zero_shot-0.2.1.dist-info/WHEEL
mengzi_zero_shot-0.2.1.dist-info/top_level.txt
mengzi_zero_shot-0.2.1.dist-info/RECORD
